torch_relativistic/__init__.py
torch_relativistic/attention.py
torch_relativistic/gnn.py
torch_relativistic/snn.py
torch_relativistic/transforms.py
torch_relativistic/utils.py
torch_relativistic-0.1.2.dist-info/METADATA
torch_relativistic-0.1.2.dist-info/WHEEL
torch_relativistic-0.1.2.dist-info/RECORD
