Metadata-Version: 2.4
Name: torch_relativistic
Version: 0.1.2
Summary: A PyTorch extension that implements neural network components inspired by relativistic physics, particularly the Terrell-Penrose effect.
Author: Björn Bethge
Requires-Python: >=3.11
Requires-Dist: torch-geometric>=2.6.1
Provides-Extra: dev
Requires-Dist: black>=25.1.0; extra == 'dev'
Requires-Dist: mypy>=1.15.0; extra == 'dev'
Requires-Dist: pytest>=8.3.5; extra == 'dev'
Requires-Dist: ruff>=0.11.9; extra == 'dev'
